Metadata-Version: 2.1
Name: uuid-shortener
Version: 0.1.3
Summary: A utility to shorten UUIDs using base62 encoding.
Home-page: https://github.com/sammeowww/py_uuid_shortener
Author: Sammeow Chan
Author-email: 1010hk@gmail.com
License: MIT
Keywords: uuid shortener base62
Classifier: Development Status :: 3 - Alpha
Classifier: Intended Audience :: Developers
Classifier: License :: OSI Approved :: MIT License
Classifier: Programming Language :: Python :: 3
Classifier: Programming Language :: Python :: 3.7
Classifier: Programming Language :: Python :: 3.8
Classifier: Programming Language :: Python :: 3.9
Classifier: Programming Language :: Python :: 3.10
Classifier: Programming Language :: Python :: 3.11
Classifier: Programming Language :: Python :: 3.12
License-File: LICENSE.txt
